flukit-0.1.1.dist-info/METADATA
flukit-0.1.1.dist-info/WHEEL
flukit-0.1.1.dist-info/entry_points.txt
flukit/__init__.py
flukit/align.py
flukit/refseq.py
flukit/utils.py
flukit-0.1.1.dist-info/RECORD
