Metadata-Version: 2.1
Name: flukit
Version: 0.1.1
Summary: Toolkit for influenza virus research
Author-Email: william <william_swl@163.com>
License: MIT
Requires-Python: >=3.10
Requires-Dist: biopython>=1.84
